Workbook
Name Slicer_Segment: #N/A
Name Slicer_Sub_Category: #N/A

Sheet Product Pivot Table
A7: State2 | B7: (ALL)
A9: Region | B9: Sum of Sales | C9: Sum of Discount | D9: Sum of Profit | E9: Average of Sales | F9: Sum of Quantity
A10: Central | B10: 40825.439 | C10: 41.82 | D10: 2647.1558 | E10: 221.87738 | F10: 715
A11: East | B11: 50894.336 | C11: 32.1 | D11: 6235.8894 | E11: 231.33789 | F11: 781
A12: South | B12: 34507.072 | C12: 20.2 | D12: 388.9234 | E12: 257.51546 | F12: 480
A13: West | B13: 42225.007 | C13: 30.15 | D13: 5362.767 | E13: 165.58826 | F13: 901
A14: Grand Total | B14: 168451.85 | C14: 124.27 | D14: 14634.736 | E14: 212.42352 | F14: 2877

Sheet Customer Pivot Table
A3: Region | B3: (ALL)
A4: Postal Code | B4: (ALL)
A6: Segment | B6: Count of Region
A7: Consumer | B7: 409
A8: Corporate | B8: 236
A9: Home Office | B9: 148
A10: Grand Total | B10: 793

Sheet category pivot table
A3: Category | B3: Sum of Quantity | C3: Sum of Discount | D3: Sum of Sales
A4: Furniture | B4: 636 | C4: 27.77 | D4: 53148.098
A5: Office Supplies | B5: 1749 | C5: 78.5 | D5: 45556.807
A6: Technology | B6: 492 | C6: 18 | D6: 69746.949
A7: Grand Total | B7: 2877 | C7: 124.27 | D7: 168451.85

Sheet Superstores_sales_dataset_1_
A1: Row ID | B1: State | C1: Order Date | D1: Ship Date | E1: Ship Mode | F1: Customer ID | G1: Customer Name | H1: Segment | I1: Country | J1: City | K1: State2 | L1: Postal Code | M1: Region | N1: Product ID | O1: Category | P1: Sub-Category | Q1: Product Name | R1: Sales | S1: Quantity | T1: Discount | U1: Profit
A2: 1 | B2: CA | C2: 42682 | D2: 42685 | E2: Second Class | F2: CG-12520 | G2: Claire Gute | H2: Consumer | I2: United States | J2: Henderson | K2: Kentucky | L2: 42420 | M2: South | N2: FUR-BO-10001798 | O2: Furniture | P2: Bookcases | Q2: Bush Somerset Collection Bookcase | R2: 261.96 | S2: 2 | T2: 0 | U2: 41.9136
A3: 2 | B3: CA | C3: 42533 | D3: 42537 | E3: Second Class | F3: DV-13045 | G3: Darrin Van Huff | H3: Corporate | I3: United States | J3: Los Angeles | K3: California | L3: 90036 | M3: West | N3: OFF-LA-10000240 | O3: Office Supplies | P3: Labels | Q3: Self-Adhesive Address Labels for Typewriters by Universal | R3: 14.62 | S3: 2 | T3: 0 | U3: 6.8714
A4: 3 | B4: US | C4: 42288 | D4: 42295 | E4: Standard Class | F4: SO-20335 | G4: Sean O'Donnell | H4: Consumer | I4: United States | J4: Fort Lauderdale | K4: Florida | L4: 33311 | M4: South | N4: FUR-TA-10000577 | O4: Furniture | P4: Tables | Q4: Bretford CR4500 Series Slim Rectangular Table | R4: 957.5775 | S4: 5 | T4: 0.45 | U4: -383.031
A5: 4 | B5: CA | C5: 41799 | D5: 41804 | E5: Standard Class | F5: BH-11710 | G5: Brosina Hoffman | H5: Consumer | I5: United States | J5: Los Angeles | K5: California | L5: 90032 | M5: West | N5: FUR-FU-10001487 | O5: Furniture | P5: Furnishings | Q5: Eldon Expressions Wood and Plastic Desk Accessories, Cherry Wood | R5: 48.86 | S5: 7 | T5: 0 | U5: 14.1694
A6: 5 | B6: CA | C6: 42840 | D6: 42845 | E6: Standard Class | F6: AA-10480 | G6: Andrew Allen | H6: Consumer | I6: United States | J6: Concord | K6: North Carolina | L6: 28027 | M6: South | N6: OFF-PA-10002365 | O6: Office Supplies | P6: Paper | Q6: Xerox 1967 | R6: 15.552 | S6: 3 | T6: 0.2 | U6: 5.4432
A7: 6 | B7: CA | C7: 42709 | D7: 42714 | E7: Standard Class | F7: IM-15070 | G7: Irene Maddox | H7: Consumer | I7: United States | J7: Seattle | K7: Washington | L7: 98103 | M7: West | N7: OFF-BI-10003656 | O7: Office Supplies | P7: Binders | Q7: Fellowes PB200 Plastic Comb Binding Machine | R7: 407.976 | S7: 3 | T7: 0.2 | U7: 132.5922
A8: 7 | B8: US | C8: 42330 | D8: 42334 | E8: Standard Class | F8: HP-14815 | G8: Harold Pawlan | H8: Home Office | I8: United States | J8: Fort Worth | K8: Texas | L8: 76106 | M8: Central | N8: OFF-AP-10002311 | O8: Office Supplies | P8: Appliances | Q8: Holmes Replacement Filter for HEPA Air Cleaner, Very Large Room, HEPA Filter | R8: 68.81 | S8: 5 | T8: 0.8 | U8: -123.858
A9: 8 | B9: CA | C9: 41954 | D9: 41961 | E9: Standard Class | F9: PK-19075 | G9: Pete Kriz | H9: Consumer | I9: United States | J9: Madison | K9: Wisconsin | L9: 53711 | M9: Central | N9: OFF-ST-10004186 | O9: Office Supplies | P9: Storage | Q9: Stur-D-Stor Shelving, Vertical 5-Shelf: 72"H x 36"W x 18 1/2"D | R9: 665.88 | S9: 6 | T9: 0 | U9: 13.3176
A10: 9 | B10: CA | C10: 41772 | D10: 41774 | E10: Second Class | F10: AG-10270 | G10: Alejandro Grove | H10: Consumer | I10: United States | J10: West Jordan | K10: Utah | L10: 84084 | M10: West | N10: OFF-ST-10000107 | O10: Office Supplies | P10: Storage | Q10: Fellowes Super Stor/Drawer | R10: 55.5 | S10: 2 | T10: 0 | U10: 9.99
A11: 10 | B11: CA | C11: 41878 | D11: 41883 | E11: Second Class | F11: ZD-21925 | G11: Zuschuss Donatelli | H11: Consumer | I11: United States | J11: San Francisco | K11: California | L11: 94109 | M11: West | N11: OFF-AR-10003056 | O11: Office Supplies | P11: Art | Q11: Newell 341 | R11: 8.56 | S11: 2 | T11: 0 | U11: 2.4824
A12: 11 | B12: CA | C12: 42713 | D12: 42717 | E12: Standard Class | F12: KB-16585 | G12: Ken Black | H12: Corporate | I12: United States | J12: Fremont | K12: Nebraska | L12: 68025 | M12: Central | N12: OFF-AR-10000246 | O12: Office Supplies | P12: Art | Q12: Newell 318 | R12: 19.46 | S12: 7 | T12: 0 | U12: 5.0596
A13: 12 | B13: US | C13: 42932 | D13: 42934 | E13: Second Class | F13: SF-20065 | G13: Sandra Flanagan | H13: Consumer | I13: United States | J13: Philadelphia | K13: Pennsylvania | L13: 19140 | M13: East | N13: FUR-CH-10002774 | O13: Furniture | P13: Chairs | Q13: Global Deluxe Stacking Chair, Gray | R13: 71.372 | S13: 2 | T13: 0.3 | U13: -1.0196
... A794: 793 | B794: CA | C794: 42493 | D794: 42495 | E794: First Class | F794: SM-20905 | G794: Susan MacKendrick | H794: Consumer | I794: United States | J794: Newark | K794: Ohio | L794: 43055 | M794: East | N794: TEC-AC-10003832 | O794: Technology | P794: Accessories | Q794: Imation 16GB Mini TravelDrive USB 2.0 Flash Drive | R794: 132.52 | S794: 5 | T794: 0.2 | U794: 34.7865

Sheet Data Exploration
B2: SUB-CATEGORY | C2: SUM OF SALES | D2: PROFIT | F2: ADJUSTED SALES | K2: PRODUCT | L2: TOTAL ORDERS | M2: AVERAGE DISCOUNT
B3: {=_xlfn.UNIQUE(Superstores_sales_dataset_1_!P768:P794)} -> Binders | C3: =SUMIF(Superstores_sales_dataset_1_!P768:P794,"BINDERS",Superstores_sales_dataset_1_!R768:R794) -> 165.9 | D3: =SUMIF(Superstores_sales_dataset_1_!P1:P794,"BINDERS",Superstores_sales_dataset_1_!U768:U794) -> 25.023 | F3: CATEGORY | G3: AVERAGE ORDER VALUE | H3: TOTAL DISCOUNT | I3: TOTAL REVENUE | K3: {=_xlfn.UNIQUE(Superstores_sales_dataset_1_!P2:P794)} -> Bookcases | L3: =COUNTA(Superstores_sales_dataset_1_!P2:P794,"BOOKCASE") -> 794 | M3: =AVERAGEIF(Superstores_sales_dataset_1_!P2:P794,"BOOKCASES",Superstores_sales_dataset_1_!T2:T794) -> 0.18647059
B4: Accessories | C4: =SUMIF(Superstores_sales_dataset_1_!P769:P795,"ACCESSORIES",Superstores_sales_dataset_1_!R769:R795) -> 845.67 | D4: =SUMIF(Superstores_sales_dataset_1_!P2:P795,"ACCESSORIES",Superstores_sales_dataset_1_!U769:U795) -> 2.8868 | F4: Bush Somerset Collection Bookcase | G4: =AVERAGE(Superstores_sales_dataset_1_!R2) -> 261.96 | H4: 0 | I4: =SUM(Superstores_sales_dataset_1_!R2,Superstores_sales_dataset_1_!U2) -> 303.8736 | K4: Labels | L4: =COUNTA(Superstores_sales_dataset_1_!P3:P795,"LABLES") -> 793 | M4: =AVERAGEIF(Superstores_sales_dataset_1_!P3:P795,"LABELS",Superstores_sales_dataset_1_!T3:T795) -> 0.053846154
B5: Furnishings | C5: =SUMIF(Superstores_sales_dataset_1_!P770:P796,"FURNISHINGS",Superstores_sales_dataset_1_!R770:R796) -> 229.792 | D5: =SUMIF(Superstores_sales_dataset_1_!P3:P796,"FURNISHINGS",Superstores_sales_dataset_1_!U770:U796) -> 5.7568 | F5: Self-Adhesive Address Labels for Typewriters by Universal | G5: =AVERAGE(Superstores_sales_dataset_1_!R3) -> 14.62 | H5: 0 | I5: =SUM(Superstores_sales_dataset_1_!R3,Superstores_sales_dataset_1_!U3) -> 21.4914 | K5: Tables | L5: =COUNTA(Superstores_sales_dataset_1_!P4:P796,"TABLES") -> 792 | M5: =AVERAGEIF(Superstores_sales_dataset_1_!P4:P796,"TABLES",Superstores_sales_dataset_1_!T4:T796) -> 0.26071429
B6: Phones | C6: =SUMIF(Superstores_sales_dataset_1_!P771:P797,"PHONES",Superstores_sales_dataset_1_!R771:R797) -> 777.52 | D6: =SUMIF(Superstores_sales_dataset_1_!P4:P797,"PHONES",Superstores_sales_dataset_1_!U771:U797) -> 58.2996 | F6: Bretford CR4500 Series Slim Rectangular Table | G6: =AVERAGE(Superstores_sales_dataset_1_!R4) -> 957.5775 | H6: 0.45 | I6: =SUM(Superstores_sales_dataset_1_!R4,Superstores_sales_dataset_1_!U4) -> 574.5465 | K6: Furnishings | L6: =COUNTA(Superstores_sales_dataset_1_!P5:P797,"FURNISHINGS") -> 791 | M6: =AVERAGEIF(Superstores_sales_dataset_1_!P5:P797,"FURNISHINGS",Superstores_sales_dataset_1_!T5:T797) -> 0.094117647
B7: Storage | C7: =SUMIF(Superstores_sales_dataset_1_!P772:P798,"STORAGE",Superstores_sales_dataset_1_!R772:R798) -> 42.76 | D7: =SUMIF(Superstores_sales_dataset_1_!P5:P798,"STORAGE",Superstores_sales_dataset_1_!U772:U798) -> 35.9539 | F7: Eldon Expressions Wood and Plastic Desk Accessories, Cherry Wood | G7: =AVERAGE(Superstores_sales_dataset_1_!R5) -> 48.86 | H7: 0 | I7: =SUM(Superstores_sales_dataset_1_!R5,Superstores_sales_dataset_1_!U5) -> 63.0294 | K7: Paper | L7: =COUNTA(Superstores_sales_dataset_1_!P6:P798,"PAPER") -> 790 | M7: =AVERAGEIF(Superstores_sales_dataset_1_!P6:P798,"PAPER",Superstores_sales_dataset_1_!T6:T798) -> 0.079646018
B8: Art | C8: =SUMIF(Superstores_sales_dataset_1_!P773:P799,"ART",Superstores_sales_dataset_1_!R773:R799) -> 113.246 | D8: =SUMIF(Superstores_sales_dataset_1_!P6:P799,"ART",Superstores_sales_dataset_1_!U773:U799) -> 6.5367 | F8: Xerox 1967 | G8: =AVERAGE(Superstores_sales_dataset_1_!R6) -> 15.552 | H8: 0.2 | I8: =SUM(Superstores_sales_dataset_1_!R6,Superstores_sales_dataset_1_!U6) -> 20.9952 | K8: Binders | L8: =COUNTA(Superstores_sales_dataset_1_!P7:P799,"BINDERS") -> 789 | M8: =AVERAGEIF(Superstores_sales_dataset_1_!P7:P799,"BINDERS",Superstores_sales_dataset_1_!T7:T799) -> 0.39449541
B9: Tables | C9: =SUMIF(Superstores_sales_dataset_1_!P774:P800,"TABLES",Superstores_sales_dataset_1_!R774:R800) -> 161.28 | D9: =SUMIF(Superstores_sales_dataset_1_!P7:P800,"TABLES",Superstores_sales_dataset_1_!U774:U800) -> 18.96 | F9: Fellowes PB200 Plastic Comb Binding Machine | G9: =AVERAGE(Superstores_sales_dataset_1_!R7) -> 407.976 | H9: 0.2 | I9: =SUM(Superstores_sales_dataset_1_!R7,Superstores_sales_dataset_1_!U7) -> 540.5682 | K9: Appliances | L9: =COUNTA(Superstores_sales_dataset_1_!P8:P800,"APPLIANCES") -> 788 | M9: =AVERAGEIF(Superstores_sales_dataset_1_!P8:P800,"APPLIANCES",Superstores_sales_dataset_1_!T8:T800) -> 0.25121951
B10: Paper | C10: =SUMIF(Superstores_sales_dataset_1_!P775:P801,"PAPER",Superstores_sales_dataset_1_!R775:R801) -> 202.192 | D10: =SUMIF(Superstores_sales_dataset_1_!P8:P801,"PAPER",Superstores_sales_dataset_1_!U775:U801) -> 71.9952 | F10: Holmes Replacement Filter for HEPA Air Cleaner, Very Large Room, HEPA Filter | G10: =AVERAGE(Superstores_sales_dataset_1_!R8) -> 68.81 | H10: 0.8 | I10: =SUM(Superstores_sales_dataset_1_!R8,Superstores_sales_dataset_1_!U8) -> -55.048 | K10: Storage | L10: =COUNTA(Superstores_sales_dataset_1_!P9:P801,"STORAGE") -> 787 | M10: =AVERAGEIF(Superstores_sales_dataset_1_!P9:P801,"STORAGE",Superstores_sales_dataset_1_!T9:T801) -> 0.070967742
B11: Envelopes | C11: =SUMIF(Superstores_sales_dataset_1_!P776:P802,"ENVELOPES",Superstores_sales_dataset_1_!R776:R802) -> 7.28 | D11: =SUMIF(Superstores_sales_dataset_1_!P9:P802,"ENVELOPES",Superstores_sales_dataset_1_!U776:U802) -> 18.33 | F11: Stur-D-Stor Shelving, Vertical 5-Shelf: 72"H x 36"W x 18 1/2"D | G11: =AVERAGE(Superstores_sales_dataset_1_!R9) -> 665.88 | H11: 0 | I11: =SUM(Superstores_sales_dataset_1_!R9,Superstores_sales_dataset_1_!U9) -> 679.1976 | K11: Art | L11: =COUNTA(Superstores_sales_dataset_1_!P10:P802,"ART") -> 786 | M11: =AVERAGEIF(Superstores_sales_dataset_1_!P10:P802,"ART",Superstores_sales_dataset_1_!T10:T802) -> 0.076315789
B12: Appliances | C12: =SUMIF(Superstores_sales_dataset_1_!P777:P803,"APPLIANCES",Superstores_sales_dataset_1_!R777:R803) -> 48.36 | D12: =SUMIF(Superstores_sales_dataset_1_!P10:P803,"APPLIANCES",Superstores_sales_dataset_1_!U777:U803) -> 0 | F12: Fellowes Super Stor/Drawer | G12: =AVERAGE(Superstores_sales_dataset_1_!R10) -> 55.5 | H12: 0 | I12: =SUM(Superstores_sales_dataset_1_!R10,Superstores_sales_dataset_1_!U10) -> 65.49 | K12: Chairs | L12: =COUNTA(Superstores_sales_dataset_1_!P11:P803,"CAHIRS") -> 785 | M12: =AVERAGEIF(Superstores_sales_dataset_1_!P11:P803,"CHAIRS",Superstores_sales_dataset_1_!T11:T803) -> 0.17222222
B13: TOTAL | C13: =SUM(C3:C12) -> 2594 | D13: =SUM(D3:D12) -> 243.742 | F13: Newell 341 | G13: =AVERAGE(Superstores_sales_dataset_1_!R11) -> 8.56 | H13: 0 | I13: =SUM(Superstores_sales_dataset_1_!R11,Superstores_sales_dataset_1_!U11) -> 11.0424 | K13: Phones | L13: =COUNTA(Superstores_sales_dataset_1_!P12:P804,"PHONES") -> 784 | M13: =AVERAGEIF(Superstores_sales_dataset_1_!P12:P804,"PHONES",Superstores_sales_dataset_1_!T12:T804) -> 0.16307692
F14: Newell 318 | G14: =AVERAGE(Superstores_sales_dataset_1_!R12) -> 19.46 | H14: 0 | I14: =SUM(Superstores_sales_dataset_1_!R12,Superstores_sales_dataset_1_!U12) -> 24.5196 | K14: Envelopes | L14: =COUNTA(Superstores_sales_dataset_1_!P13:P805,"ENVELOPES") -> 783 | M14: =AVERAGEIF(Superstores_sales_dataset_1_!P13:P805,"ENVELOPES",Superstores_sales_dataset_1_!T13:T805) -> 0.10526316
F15: Global Deluxe Stacking Chair, Gray | G15: =AVERAGE(Superstores_sales_dataset_1_!R13) -> 71.372 | H15: 0.3 | I15: =SUM(Superstores_sales_dataset_1_!R13,Superstores_sales_dataset_1_!U13) -> 70.3524 | K15: Accessories | L15: =COUNTA(Superstores_sales_dataset_1_!P14:P806,"ACCESSORIES") -> 782 | M15: =AVERAGEIF(Superstores_sales_dataset_1_!P14:P806,"ACCESSORIES",Superstores_sales_dataset_1_!T14:T806) -> 0.062295082
B16: REGION | C16: PROFIT | D16: SALES | F16: Bretford CR4500 Series Slim Rectangular Table | G16: =AVERAGE(Superstores_sales_dataset_1_!R14) -> 1044.63 | H16: 0 | I16: =SUM(Superstores_sales_dataset_1_!R14,Superstores_sales_dataset_1_!U14) -> 1284.8949 | K16: Fasteners | L16: =COUNTA(Superstores_sales_dataset_1_!P15:P807,"FASTENERS") -> 781 | M16: =AVERAGEIF(Superstores_sales_dataset_1_!P15:P807,"FASTENERS",Superstores_sales_dataset_1_!T15:T807) -> 0.0875
B17: {=_xlfn.UNIQUE(Superstores_sales_dataset_1_!M768:M794)} -> East | C17: =SUMIF(Superstores_sales_dataset_1_!M768:M794,"EAST",Superstores_sales_dataset_1_!U768:U794) -> 104.1632 | D17: =SUMIF(Superstores_sales_dataset_1_!M765:M791,"EAST",Superstores_sales_dataset_1_!R765:R791) -> 392.74 | F17: Wilson Jones Active Use Binders | G17: =AVERAGE(Superstores_sales_dataset_1_!R15) -> 11.648 | H17: 0.2 | I17: =SUM(Superstores_sales_dataset_1_!R15,Superstores_sales_dataset_1_!U15) -> 15.8704 | K17: Machines | L17: =COUNTA(Superstores_sales_dataset_1_!P16:P808,"MACHINES") -> 780 | M17: =AVERAGEIF(Superstores_sales_dataset_1_!P16:P808,"MACHINES",Superstores_sales_dataset_1_!T16:T808) -> 0.4
B18: South | C18: =SUMIF(Superstores_sales_dataset_1_!M769:M795,"SOUTH",Superstores_sales_dataset_1_!U769:U795) -> 299.4848 | D18: =SUMIF(Superstores_sales_dataset_1_!M766:M792,"SOUTH",Superstores_sales_dataset_1_!R766:R792) -> 909.622 | F18: Riverside Palais Royal Lawyers Bookcase, Royale Cherry Finish | G18: =AVERAGE(Superstores_sales_dataset_1_!R16) -> 3083.43 | H18: 0.5 | I18: =SUM(Superstores_sales_dataset_1_!R16,Superstores_sales_dataset_1_!U16) -> 1418.3778 | K18: Supplies | L18: =COUNTA(Superstores_sales_dataset_1_!P17:P809,"SUPPLIES") -> 779 | M18: =AVERAGEIF(Superstores_sales_dataset_1_!P17:P809,"SUPPLIES",Superstores_sales_dataset_1_!T17:T809) -> 0.10909091
B19: West | C19: =SUMIF(Superstores_sales_dataset_1_!M770:M796,"WEST",Superstores_sales_dataset_1_!U770:U796) -> 53.8188 | D19: =SUMIF(Superstores_sales_dataset_1_!M767:M793,"WEST",Superstores_sales_dataset_1_!R767:R793) -> 314.728 | F19: Easy-staple paper | G19: =AVERAGE(Superstores_sales_dataset_1_!R17) -> 29.472 | H19: 0.2 | I19: =SUM(Superstores_sales_dataset_1_!R17,Superstores_sales_dataset_1_!U17) -> 39.4188 | K19: Copiers | L19: =COUNTA(Superstores_sales_dataset_1_!P18:P810,"COPIERS") -> 778 | M19: =AVERAGEIF(Superstores_sales_dataset_1_!P18:P810,"COPIERS",Superstores_sales_dataset_1_!T18:T810) -> 0.3
B20: Central | C20: =SUMIF(Superstores_sales_dataset_1_!M771:M797,"CENTRAL",Superstores_sales_dataset_1_!U771:U797) -> 146.1813 | D20: =SUMIF(Superstores_sales_dataset_1_!M768:M794,"EAST",Superstores_sales_dataset_1_!R768:R794) -> 408.74 | F20: GE 30524EE4 | G20: =AVERAGE(Superstores_sales_dataset_1_!R18) -> 1097.544 | H20: 0.2 | I20: =SUM(Superstores_sales_dataset_1_!R18,Superstores_sales_dataset_1_!U18) -> 1221.0177 | K20: TOTAL | L20: =SUM(L3:L19) -> 13362 | M20: =SUM(M3:M19) -> 2.8672414
B21: TOTAL | C21: =SUM(C17:C20) -> 603.6481 | D21: =SUM(D17:D20) -> 2025.83 | F21: #10-4 1/8" x 9 1/2" Premium Diagonal Seam Envelopes | G21: =AVERAGE(Superstores_sales_dataset_1_!R19) -> 113.328 | H21: 0.2 | I21: =SUM(Superstores_sales_dataset_1_!R19,Superstores_sales_dataset_1_!U19) -> 148.743
F22: Panasonic Kx-TS550 | G22: =AVERAGE(Superstores_sales_dataset_1_!R20) -> 147.168 | H22: 0.2 | I22: =SUM(Superstores_sales_dataset_1_!R20,Superstores_sales_dataset_1_!U20) -> 163.7244
F23: Eldon Base for stackable storage shelf, platinum | G23: =AVERAGE(Superstores_sales_dataset_1_!R21) -> 77.88 | H23: 0 | I23: =SUM(Superstores_sales_dataset_1_!R21,Superstores_sales_dataset_1_!U21) -> 81.774
F24: Advantus 10-Drawer Portable Organizer, Chrome Metal Frame, Smoke Drawers | G24: =AVERAGE(Superstores_sales_dataset_1_!R22) -> 95.616 | H24: 0.2 | I24: =SUM(Superstores_sales_dataset_1_!R22,Superstores_sales_dataset_1_!U22) -> 105.1776
F25: Verbatim 25 GB 6x Blu-ray Single Layer Recordable Disc, 25/Pack | G25: =AVERAGE(Superstores_sales_dataset_1_!R23) -> 45.98 | H25: 0 | I25: =SUM(Superstores_sales_dataset_1_!R23,Superstores_sales_dataset_1_!U23) -> 65.7514
F26: Gould Plastics 9-Pocket Panel Bin, 18-3/8w x 5-1/4d x 20-1/2h, Black | G26: =AVERAGE(Superstores_sales_dataset_1_!R24) -> 211.96 | H26: 0 | I26: =SUM(Superstores_sales_dataset_1_!R24,Superstores_sales_dataset_1_!U24) -> 220.4384
F27: Imation 8gb Micro Traveldrive Usb 2.0 Flash Drive | G27: =AVERAGE(Superstores_sales_dataset_1_!R25) -> 45 | H27: 0 | I27: =SUM(Superstores_sales_dataset_1_!R25,Superstores_sales_dataset_1_!U25) -> 49.95
F28: C-Line Peel & Stick Add-On Filing Pockets, 8-3/4 x 5-1/8, 10/Pack | G28: =AVERAGE(Superstores_sales_dataset_1_!R26) -> 38.22 | H28: 0 | I28: =SUM(Superstores_sales_dataset_1_!R26,Superstores_sales_dataset_1_!U26) -> 56.1834
F29: Advantus Push Pins | G29: =AVERAGE(Superstores_sales_dataset_1_!R27) -> 15.26 | H29: 0 | I29: =SUM(Superstores_sales_dataset_1_!R27,Superstores_sales_dataset_1_!U27) -> 21.5166
F30: Home/Office Personal File Carts | G30: =AVERAGE(Superstores_sales_dataset_1_!R28) -> 208.56 | H30: 0 | I30: =SUM(Superstores_sales_dataset_1_!R28,Superstores_sales_dataset_1_!U28) -> 260.7
F31: Verbatim 25 GB 6x Blu-ray Single Layer Recordable Disc, 3/Pack | G31: =AVERAGE(Superstores_sales_dataset_1_!R29) -> 13.98 | H31: 0 | I31: =SUM(Superstores_sales_dataset_1_!R29,Superstores_sales_dataset_1_!U29) -> 20.1312
F32: Global Value Mid-Back Manager's Chair, Gray | G32: =AVERAGE(Superstores_sales_dataset_1_!R30) -> 213.115 | H32: 0.3 | I32: =SUM(Superstores_sales_dataset_1_!R30,Superstores_sales_dataset_1_!U30) -> 197.8925
F33: Hunt BOSTON Model 1606 High-Volume Electric Pencil Sharpener, Beige | G33: =AVERAGE(Superstores_sales_dataset_1_!R31) -> 1113.024 | H33: 0.2 | I33: =SUM(Superstores_sales_dataset_1_!R31,Superstores_sales_dataset_1_!U31) -> 1224.3264
... F796: Imation 16GB Mini TravelDrive USB 2.0 Flash Drive | G796: =AVERAGE(Superstores_sales_dataset_1_!R794) -> 132.52 | H796: 0.2 | I796: =SUM(Superstores_sales_dataset_1_!R794,Superstores_sales_dataset_1_!U794) -> 167.3065
F797: TOTAL | G797: =AVERAGE(G4:G796) -> 212.42352 | H797: =SUM(H4:H796) -> 124.27 | I797: =SUM(I4:I796) -> 183086.59

Sheet Dashboard
